Metadata-Version: 1.1
Name: integrate
Version: 1.1.0
Summary: Test framework for integration tests with dependencies
Home-page: https://github.com/anfema/integrate
Author: Johannes Schriewer
Author-email: hallo@dunkelstern.de
License: BSD
Keywords: integration test tests
Platform: UNKNOWN
Classifier: Development Status :: 4 - Beta
Classifier: Intended Audience :: Developers
Classifier: Topic :: Software Development :: Testing
Classifier: License :: OSI Approved :: BSD License
Classifier: Programming Language :: Python :: 2.7
Classifier: Programming Language :: Python :: 3.3
Classifier: Programming Language :: Python :: 3.4
Classifier: Programming Language :: Python :: 3.5
